zoey/__init__.py
zoey/cli.py
zoey/scopes/__init__.py
zoey/scopes/generators.py
zoey/scopes/groups.py
zoey/scopes/pages.py
zoey/scopes/sites.py
zoey/templates/page_base/single_page.md
zoey/templates/project_base/config.py
zoey/templates/project_base/public/.gitkeep
zoey/templates/project_base/src/.gitkeep
zoey/templates/project_base/src/index.md
zoey/templates/project_base/src/assets/style-dark.css
zoey/templates/project_base/src/assets/style.css
zoey/templates/project_base/src/assets/media/.gitkeep
zoey-0.4.0.dist-info/METADATA
zoey-0.4.0.dist-info/WHEEL
zoey-0.4.0.dist-info/entry_points.txt
zoey-0.4.0.dist-info/top_level.txt
zoey-0.4.0.dist-info/RECORD
