Metadata-Version: 2.1
Name: zoey
Version: 0.4.0
Summary: Zoey is a command line static site generator, written in Python.
Home-page: https://github.com/ITSSOUMIT/zoey
Author: Soumit Das
Author-email: me@soumit.in
Classifier: Programming Language :: Python :: 3
Classifier: License :: OSI Approved :: MIT License
Classifier: Operating System :: OS Independent
Requires-Python: >=3.6
Requires-Dist: click
Requires-Dist: markdown
